{
  "workout": {
    "name": "تأهيل الاصابة",
    "days": 1,
    "createdAt": "2025-11-05T14:30:57.923Z",
    "day1": {
      "dayName": "يوم 1",
      "exercises": [
        {
          "name": "Y raises",
          "sets": 3,
          "singleArm": false,
          "image": "https://liftmanual.com/wp-content/uploads/2023/04/dumbbell-incline-y-raise.jpg"
        },
        {
          "name": "Serratus anterior",
          "sets": 3,
          "singleArm": false,
          "image": "https://weighttraining.guide/wp-content/uploads/2016/12/machine-chest-press-resized.png"
        },
        {
          "name": "rear delt fly",
          "sets": 3,
          "singleArm": false,
          "image": "https://miro.medium.com/1*GrUZ3L1DEGvcHwW6EIRe7w.jpeg"
        },
        {
          "name": "dumbell lateral raise",
          "sets": 3,
          "singleArm": false,
          "image": "https://weighttraining.guide/wp-content/uploads/2016/05/dumbbell-lateral-raise-resized.png"
        },
        {
          "name": "cable front raise",
          "sets": 3,
          "singleArm": true,
          "image": "https://images.squarespace-cdn.com/content/v1/5ffcea9416aee143500ea103/1637854995298-0QU223L22UX8ZQ9SNVF4/One%2BArm%2BCable%2BFront%2BRaises.jpeg"
        },
        {
          "name": "shrugs",
          "sets": 3,
          "singleArm": false,
          "image": "https://training.fit/wp-content/uploads/2020/02/shrugs-kabelzug.png"
        },
        {
          "name": "lat pull down",
          "sets": 3,
          "singleArm": false,
          "image": "https://training.fit/wp-content/uploads/2020/02/latzug.png"
        }
      ]
    }
  },
  "records": []
}
